LICENSE
MANIFEST.in
README.rst
setup.cfg
setup.py
r_django_essentials/__init__.py
r_django_essentials/apps.py
r_django_essentials/conf.py
r_django_essentials/deprecation.py
r_django_essentials/enumtest.py
r_django_essentials/fields.py
r_django_essentials/logging.py
r_django_essentials/tests.py
r_django_essentials/formats/__init__.py
r_django_essentials/formats/en/__init__.py
r_django_essentials/formats/en/formats.py
r_django_essentials/formats/fi/__init__.py
r_django_essentials/formats/fi/formats.py
r_django_essentials/jinja2/__init__.py
r_django_essentials/jinja2/extensions.py
r_django_essentials/utils/__init__.py
r_django_essentials/utils/common.py
r_django_essentials/utils/conf.py
r_django_essentials/utils/django.py
r_django_essentials/utils/importing.py
raphendyr_django_essentials.egg-info/PKG-INFO
raphendyr_django_essentials.egg-info/SOURCES.txt
raphendyr_django_essentials.egg-info/dependency_links.txt
raphendyr_django_essentials.egg-info/requires.txt
raphendyr_django_essentials.egg-info/top_level.txt